{
    "costos-terminaciones-sevicios": {
        "aberturas - estimado": "",
        "puertas y puerta principal": "",
        "losa radiante eléctrica": "",
        "losa radiante de agua y caldera": "",
        "agua": "",
        "aire acondicionado": "",
        "artefactos": "",
        "cloaca": "",
        "electricidad": "",
        "gas": "",
        "revestiento plastico paredes externas mat_m.o": "",
        "empastado y pintado de cielorraso_interno": "",
        "mueble de cocin placares": "",
        "piedra o mesada de mueble de cocina": "",
        "detalles en chapa - molduras- cumbrera garganta de hogar": "",
        "zingueria y desagüe pluvial con zinguero": "",
        "instalación de artefactos_sanitarios_eléctricos.": "",
        "pisos_huella de la casa, galeria y cochera": "",
        "zócalos de madera_porcelanato_a_definir": "",
        "fletes-contenedores-limpieza final del terreno_nivelación": "",
        "ladrillo refractario": ""
    }
}
